{"upload_date": "20170422", "vcodec": "avc1.4d400b", "extractor": "youtube", "series": null, "chapters": null, "height": 144, "like_count": 6, "duration": 739, "fulltitle": "\u4e2d\u7f8e\u5bb6\u5ead\u5173\u7cfb\u5bf9\u6bd4", "id": "yWNAOKfw2qk", "album": null, "view_count": 272, "playlist": "Uploads from Faye Hu", "start_time": null, "title": "\u4e2d\u7f8e\u5bb6\u5ead\u5173\u7cfb\u5bf9\u6bd4", "_filename": "20170422_NA_yWNAOKfw2qk.mp4", "creator": null, "is_live": null, "playlist_index": 154, "dislike_count": 0, "playlist_id": "UUheuDxi3s2WAefGCbLHwqAw", "abr": 48, "tags": [], "uploader_url": "http://www.youtube.com/channel/UCheuDxi3s2WAefGCbLHwqAw", "subtitles": {}, "fps": 30, "stretched_ratio": null, "season_number": null, "annotations": null, "webpage_url_basename": "yWNAOKfw2qk", "acodec": "mp4a.40.5", "display_id": "yWNAOKfw2qk", "automatic_captions": {}, "description": "", "format": "160 - 256x144 (DASH video)+139 - audio only (DASH audio)", "track": null, "playlist_uploader": "Faye Hu", "average_rating": null, "uploader": "Faye Hu", "format_id": "160+139", "episode_number": null, "uploader_id": "UCheuDxi3s2WAefGCbLHwqAw", "categories": ["Entertainment"], "playlist_title": "Uploads from Faye Hu", "thumbnails": [{"url": "https://i.ytimg.com/vi/yWNAOKfw2qk/maxresdefault.jpg", "id": "0"}], "license": null, "artist": null, "extractor_key": "Youtube", "release_date": null, "alt_title": null, "channel_id": "UCheuDxi3s2WAefGCbLHwqAw", "thumbnail": "https://i.ytimg.com/vi/yWNAOKfw2qk/maxresdefault.jpg", "vbr": null, "ext": "mp4", "release_year": null, "end_time": null, "webpage_url": "https://www.youtube.com/watch?v=yWNAOKfw2qk", "formats": [{"asr": 22050, "tbr": 52.119, "protocol": "http_dash_segments", "format": "139 - audio only (DASH audio)", "format_note": "DASH audio", "height": null, "manifest_url": "https://manifest.googlevideo.com/api/manifest/dash/requiressl/yes/source/youtube/id/c9634038a7f0daa9/itag/0/ei/vNnRXIr0I8bgkgaK0rvAAg/playback_host/r6---sn-a5mlrn7k.googlevideo.com/mm/31%2C29/mn/sn-a5mlrn7k%2Csn-a5meknee/ms/au%2Crdu/mv/u/pl/21/hfr/all/as/fmp4_audio_clear%2Cwebm_audio_clear%2Cwebm2_audio_clear%2Cfmp4_sd_hd_clear%2Cwebm2_sd_hd_clear/mt/1557255740/fvip/4/ip/155.94.169.201/ipbits/0/expire/1557278236/sparams/ip%2Cipbits%2Cexpire%2Crequiressl%2Csource%2Cid%2Citag%2Cei%2Cplayback_host%2Cmm%2Cmn%2Cms%2Cmv%2Cpl%2Chfr%2Cas/signature/849D19C69FFBBD64D4FAC80C68938559B44A27A8.7BC9768FD70DBD4F8FEE2C278E2C73E570AFF867/key/yt8", "format_id": "139", "container": "m4a_dash", "language": null, "http_headers": {"Accept-Charset": "ISO-8859-1,utf-8;q=0.7,*;q=0.7", "Accept-Language": "en-us,en;q=0.5", "Accept-Encoding": "gzip, deflate", "Accept": "text/html,application/xhtml+xml,application/xml;q=0.9,*/*;q=0.8", "User-Agent": "Mozilla/5.0 (X11; Linux x86_64; rv:59.0) Gecko/20100101 Firefox/59.0"}, "url": "https://manifest.googlevideo.com/api/manifest/dash/requiressl/yes/source/youtube/id/c9634038a7f0daa9/itag/0/ei/vNnRXIr0I8bgkgaK0rvAAg/playback_host/r6---sn-a5mlrn7k.googlevideo.com/mm/31%2C29/mn/sn-a5mlrn7k%2Csn-a5meknee/ms/au%2Crdu/mv/u/pl/21/hfr/all/as/fmp4_audio_clear%2Cwebm_audio_clear%2Cwebm2_audio_clear%2Cfmp4_sd_hd_clear%2Cwebm2_sd_hd_clear/mt/1557255740/fvip/4/ip/155.94.169.201/ipbits/0/expire/1557278236/sparams/ip%2Cipbits%2Cexpire%2Crequiressl%2Csource%2Cid%2Citag%2Cei%2Cplayback_host%2Cmm%2Cmn%2Cms%2Cmv%2Cpl%2Chfr%2Cas/signature/849D19C69FFBBD64D4FAC80C68938559B44A27A8.7BC9768FD70DBD4F8FEE2C278E2C73E570AFF867/key/yt8", "vcodec": "none", "abr": 48, "width": null, "ext": "m4a", "fragment_base_url": "https://r6---sn-a5mlrn7k.googlevideo.com/videoplayback/id/c9634038a7f0daa9/itag/139/source/youtube/requiressl/yes/ei/vNnRXIr0I8bgkgaK0rvAAg/mm/31,29/mn/sn-a5mlrn7k,sn-a5meknee/ms/au,rdu/mv/u/pl/21/ratebypass/yes/mime/audio%2Fmp4/otfp/1/gir/yes/clen/4402942/lmt/1492905494775776/dur/738.812/mt/1557255740/fvip/4/disable_polymer/true/ip/155.94.169.201/ipbits/0/expire/1557278236/sparams/ip,ipbits,expire,id,itag,source,requiressl,ei,mm,mn,ms,mv,pl,ratebypass,mime,otfp,gir,clen,lmt,dur/signature/98D371C5CAB59C64F87D33447D0D1E5C9D2AA1C6.4CAEE76637E9F51A351B5ED09B1AE891EF86C5DE/key/dg_yt0/", "filesize": null, "fps": null, "fragments": [{"path": "range/0-593"}, {"duration": 5.016, "path": "range/2402-32678"}, {"duration": 5.015, "path": "range/32679-62600"}, {"duration": 4.969, "path": "range/62601-92013"}, {"duration": 5.016, "path": "range/92014-121967"}, {"duration": 5.015, "path": "range/121968-151700"}, {"duration": 4.969, "path": "range/151701-181582"}, {"duration": 5.016, "path": "range/181583-211284"}, {"duration": 5.015, "path": "range/211285-241413"}, {"duration": 4.969, "path": "range/241414-270768"}, {"duration": 5.016, "path": "range/270769-300596"}, {"duration": 5.015, "path": "range/300597-330614"}, {"duration": 4.969, "path": "range/330615-360140"}, {"duration": 5.016, "path": "range/360141-390039"}, {"duration": 5.015, "path": "range/390040-419771"}, {"duration": 4.969, "path": "range/419772-449483"}, {"duration": 5.016, "path": "range/449484-479426"}, {"duration": 5.015, "path": "range/479427-509262"}, {"duration": 4.97, "path": "range/509263-538787"}, {"duration": 5.015, "path": "range/538788-568749"}, {"duration": 5.016, "path": "range/568750-598599"}, {"duration": 4.969, "path": "range/598600-628239"}, {"duration": 5.015, "path": "range/628240-657915"}, {"duration": 5.016, "path": "range/657916-687752"}, {"duration": 4.969, "path": "range/687753-717474"}, {"duration": 5.015, "path": "range/717475-747360"}, {"duration": 5.016, "path": "range/747361-777293"}, {"duration": 4.969, "path": "range/777294-807033"}, {"duration": 5.015, "path": "range/807034-836837"}, {"duration": 5.016, "path": "range/836838-866734"}, {"duration": 4.969, "path": "range/866735-896209"}, {"duration": 5.015, "path": "range/896210-926221"}, {"duration": 5.016, "path": "range/926222-955921"}, {"duration": 4.969, "path": "range/955922-985496"}, {"duration": 5.015, "path": "range/985497-1015602"}, {"duration": 5.016, "path": "range/1015603-1045390"}, {"duration": 4.969, "path": "range/1045391-1074852"}, {"duration": 5.016, "path": "range/1074853-1104731"}, {"duration": 5.015, "path": "range/1104732-1134728"}, {"duration": 4.969, "path": "range/1134729-1164320"}, {"duration": 5.016, "path": "range/1164321-1194073"}, {"duration": 5.015, "path": "range/1194074-1223856"}, {"duration": 4.969, "path": "range/1223857-1253582"}, {"duration": 5.016, "path": "range/1253583-1283488"}, {"duration": 5.015, "path": "range/1283489-1313241"}, {"duration": 4.969, "path": "range/1313242-1342985"}, {"duration": 5.016, "path": "range/1342986-1372873"}, {"duration": 5.015, "path": "range/1372874-1402802"}, {"duration": 4.969, "path": "range/1402803-1432186"}, {"duration": 5.016, "path": "range/1432187-1462176"}, {"duration": 5.015, "path": "range/1462177-1491835"}, {"duration": 4.97, "path": "range/1491836-1521617"}, {"duration": 5.015, "path": "range/1521618-1551549"}, {"duration": 5.016, "path": "range/1551550-1581205"}, {"duration": 4.969, "path": "range/1581206-1611195"}, {"duration": 5.015, "path": "range/1611196-1640858"}, {"duration": 5.016, "path": "range/1640859-1670639"}, {"duration": 4.969, "path": "range/1670640-1700237"}, {"duration": 5.015, "path": "range/1700238-1730235"}, {"duration": 5.016, "path": "range/1730236-1760073"}, {"duration": 4.969, "path": "range/1760074-1789483"}, {"duration": 5.015, "path": "range/1789484-1819603"}, {"duration": 5.016, "path": "range/1819604-1849281"}, {"duration": 4.969, "path": "range/1849282-1878890"}, {"duration": 5.015, "path": "range/1878891-1908733"}, {"duration": 5.016, "path": "range/1908734-1938668"}, {"duration": 4.969, "path": "range/1938669-1968296"}, {"duration": 5.015, "path": "range/1968297-1998178"}, {"duration": 5.016, "path": "range/1998179-2027996"}, {"duration": 4.969, "path": "range/2027997-2057685"}, {"duration": 5.016, "path": "range/2057686-2087459"}, {"duration": 5.015, "path": "range/2087460-2117419"}, {"duration": 4.969, "path": "range/2117420-2147018"}, {"duration": 5.016, "path": "range/2147019-2176877"}, {"duration": 5.015, "path": "range/2176878-2206706"}, {"duration": 4.969, "path": "range/2206707-2236355"}, {"duration": 5.016, "path": "range/2236356-2266199"}, {"duration": 5.015, "path": "range/2266200-2296185"}, {"duration": 4.969, "path": "range/2296186-2325580"}, {"duration": 5.016, "path": "range/2325581-2355586"}, {"duration": 5.015, "path": "range/2355587-2385393"}, {"duration": 4.969, "path": "range/2385394-2414964"}, {"duration": 5.016, "path": "range/2414965-2444893"}, {"duration": 5.015, "path": "range/2444894-2474878"}, {"duration": 4.97, "path": "range/2474879-2504481"}, {"duration": 5.015, "path": "range/2504482-2534385"}, {"duration": 5.016, "path": "range/2534386-2564006"}, {"duration": 4.969, "path": "range/2564007-2593802"}, {"duration": 5.015, "path": "range/2593803-2623503"}, {"duration": 5.016, "path": "range/2623504-2653439"}, {"duration": 4.969, "path": "range/2653440-2683156"}, {"duration": 5.015, "path": "range/2683157-2712724"}, {"duration": 5.016, "path": "range/2712725-2742700"}, {"duration": 4.969, "path": "range/2742701-2772339"}, {"duration": 5.015, "path": "range/2772340-2802308"}, {"duration": 5.016, "path": "range/2802309-2832037"}, {"duration": 4.969, "path": "range/2832038-2861898"}, {"duration": 5.015, "path": "range/2861899-2891645"}, {"duration": 5.016, "path": "range/2891646-2921322"}, {"duration": 4.969, "path": "range/2921323-2951131"}, {"duration": 5.015, "path": "range/2951132-2981059"}, {"duration": 5.016, "path": "range/2981060-3010927"}, {"duration": 4.969, "path": "range/3010928-3040515"}, {"duration": 5.016, "path": "range/3040516-3070203"}, {"duration": 5.015, "path": "range/3070204-3100308"}, {"duration": 4.969, "path": "range/3100309-3129844"}, {"duration": 5.016, "path": "range/3129845-3159613"}, {"duration": 5.015, "path": "range/3159614-3189556"}, {"duration": 4.969, "path": "range/3189557-3219050"}, {"duration": 5.016, "path": "range/3219051-3249012"}, {"duration": 5.015, "path": "range/3249013-3278822"}, {"duration": 4.969, "path": "range/3278823-3308479"}, {"duration": 5.016, "path": "range/3308480-3338281"}, {"duration": 5.015, "path": "range/3338282-3368146"}, {"duration": 4.969, "path": "range/3368147-3397778"}, {"duration": 5.016, "path": "range/3397779-3427612"}, {"duration": 5.015, "path": "range/3427613-3457747"}, {"duration": 4.97, "path": "range/3457748-3487194"}, {"duration": 5.015, "path": "range/3487195-3517171"}, {"duration": 5.016, "path": "range/3517172-3546890"}, {"duration": 4.969, "path": "range/3546891-3576534"}, {"duration": 5.015, "path": "range/3576535-3606463"}, {"duration": 5.016, "path": "range/3606464-3636286"}, {"duration": 4.969, "path": "range/3636287-3665674"}, {"duration": 5.015, "path": "range/3665675-3695829"}, {"duration": 5.016, "path": "range/3695830-3725659"}, {"duration": 4.969, "path": "range/3725660-3755154"}, {"duration": 5.015, "path": "range/3755155-3785243"}, {"duration": 5.016, "path": "range/3785244-3814871"}, {"duration": 4.969, "path": "range/3814872-3844743"}, {"duration": 5.015, "path": "range/3844744-3874616"}, {"duration": 5.016, "path": "range/3874617-3904290"}, {"duration": 4.969, "path": "range/3904291-3934012"}, {"duration": 5.015, "path": "range/3934013-3963579"}, {"duration": 5.016, "path": "range/3963580-3993720"}, {"duration": 4.969, "path": "range/3993721-4023239"}, {"duration": 5.016, "path": "range/4023240-4053122"}, {"duration": 5.015, "path": "range/4053123-4082921"}, {"duration": 4.969, "path": "range/4082922-4112392"}, {"duration": 5.016, "path": "range/4112393-4142466"}, {"duration": 5.015, "path": "range/4142467-4172285"}, {"duration": 4.969, "path": "range/4172286-4201926"}, {"duration": 5.016, "path": "range/4201927-4231815"}, {"duration": 5.015, "path": "range/4231816-4261668"}, {"duration": 4.969, "path": "range/4261669-4291107"}, {"duration": 5.016, "path": "range/4291108-4321088"}, {"duration": 5.015, "path": "range/4321089-4350843"}, {"duration": 4.969, "path": "range/4350844-4380549"}, {"duration": 3.808, "path": "range/4380550-4402941"}], "acodec": "mp4a.40.5"}, {"asr": 44100, "tbr": 131.362, "protocol": "http_dash_segments", "format": "140 - audio only (DASH audio)", "format_note": "DASH audio", "height": null, "manifest_url": "https://manifest.googlevideo.com/api/manifest/dash/requiressl/yes/source/youtube/id/c9634038a7f0daa9/itag/0/ei/vNnRXIr0I8bgkgaK0rvAAg/playback_host/r6---sn-a5mlrn7k.googlevideo.com/mm/31%2C29/mn/sn-a5mlrn7k%2Csn-a5meknee/ms/au%2Crdu/mv/u/pl/21/hfr/all/as/fmp4_audio_clear%2Cwebm_audio_clear%2Cwebm2_audio_clear%2Cfmp4_sd_hd_clear%2Cwebm2_sd_hd_clear/mt/1557255740/fvip/4/ip/155.94.169.201/ipbits/0/expire/1557278236/sparams/ip%2Cipbits%2Cexpire%2Crequiressl%2Csource%2Cid%2Citag%2Cei%2Cplayback_host%2Cmm%2Cmn%2Cms%2Cmv%2Cpl%2Chfr%2Cas/signature/849D19C69FFBBD64D4FAC80C68938559B44A27A8.7BC9768FD70DBD4F8FEE2C278E2C73E570AFF867/key/yt8", "format_id": "140", "container": "m4a_dash", "language": null, "http_headers": {"Accept-Charset": "ISO-8859-1,utf-8;q=0.7,*;q=0.7", "Accept-Language": "en-us,en;q=0.5", "Accept-Encoding": "gzip, deflate", "Accept": "text/html,application/xhtml+xml,application/xml;q=0.9,*/*;q=0.8", "User-Agent": "Mozilla/5.0 (X11; Linux x86_64; rv:59.0) Gecko/20100101 Firefox/59.0"}, "url": "https://manifest.googlevideo.com/api/manifest/dash/requiressl/yes/source/youtube/id/c9634038a7f0daa9/itag/0/ei/vNnRXIr0I8bgkgaK0rvAAg/playback_host/r6---sn-a5mlrn7k.googlevideo.com/mm/31%2C29/mn/sn-a5mlrn7k%2Csn-a5meknee/ms/au%2Crdu/mv/u/pl/21/hfr/all/as/fmp4_audio_clear%2Cwebm_audio_clear%2Cwebm2_audio_clear%2Cfmp4_sd_hd_clear%2Cwebm2_sd_hd_clear/mt/1557255740/fvip/4/ip/155.94.169.201/ipbits/0/expire/1557278236/sparams/ip%2Cipbits%2Cexpire%2Crequiressl%2Csource%2Cid%2Citag%2Cei%2Cplayback_host%2Cmm%2Cmn%2Cms%2Cmv%2Cpl%2Chfr%2Cas/signature/849D19C69FFBBD64D4FAC80C68938559B44A27A8.7BC9768FD70DBD4F8FEE2C278E2C73E570AFF867/key/yt8", "vcodec": "none", "abr": 128, "width": null, "ext": "m4a", "fragment_base_url": "https://r6---sn-a5mlrn7k.googlevideo.com/videoplayback/id/c9634038a7f0daa9/itag/140/source/youtube/requiressl/yes/ei/vNnRXIr0I8bgkgaK0rvAAg/mm/31,29/mn/sn-a5mlrn7k,sn-a5meknee/ms/au,rdu/mv/u/pl/21/ratebypass/yes/mime/audio%2Fmp4/otfp/1/gir/yes/clen/11741864/lmt/1492905493682212/dur/738.719/mt/1557255740/fvip/4/disable_polymer/true/ip/155.94.169.201/ipbits/0/expire/1557278236/sparams/ip,ipbits,expire,id,itag,source,requiressl,ei,mm,mn,ms,mv,pl,ratebypass,mime,otfp,gir,clen,lmt,dur/signature/655636791F4F4059EE52A1A2089D4C046AEADCB8.274AB9E75EB906E46862CE32129BB24B10115EA8/key/dg_yt0/", "filesize": null, "fps": null, "fragments": [{"path": "range/0-591"}, {"duration": 5.016, "path": "range/2400-82363"}, {"duration": 5.015, "path": "range/82364-161640"}, {"duration": 4.969, "path": "range/161641-240979"}, {"duration": 5.016, "path": "range/240980-320526"}, {"duration": 5.015, "path": "range/320527-399856"}, {"duration": 4.969, "path": "range/399857-479261"}, {"duration": 5.016, "path": "range/479262-558991"}, {"duration": 5.015, "path": "range/558992-638333"}, {"duration": 4.969, "path": "range/638334-717747"}, {"duration": 5.016, "path": "range/717748-797321"}, {"duration": 5.015, "path": "range/797322-876711"}, {"duration": 4.969, "path": "range/876712-955966"}, {"duration": 5.016, "path": "range/955967-1035730"}, {"duration": 5.015, "path": "range/1035731-1115238"}, {"duration": 4.969, "path": "range/1115239-1194589"}, {"duration": 5.016, "path": "range/1194590-1274359"}, {"duration": 5.015, "path": "range/1274360-1353424"}, {"duration": 4.97, "path": "range/1353425-1432763"}, {"duration": 5.015, "path": "range/1432764-1512557"}, {"duration": 5.016, "path": "range/1512558-1591898"}, {"duration": 4.969, "path": "range/1591899-1671213"}, {"duration": 5.015, "path": "range/1671214-1750816"}, {"duration": 5.016, "path": "range/1750817-1830149"}, {"duration": 4.969, "path": "range/1830150-1909586"}, {"duration": 5.015, "path": "range/1909587-1989403"}, {"duration": 5.016, "path": "range/1989404-2068512"}, {"duration": 4.969, "path": "range/2068513-2147929"}, {"duration": 5.015, "path": "range/2147930-2227673"}, {"duration": 5.016, "path": "range/2227674-2307018"}, {"duration": 4.969, "path": "range/2307019-2386404"}, {"duration": 5.015, "path": "range/2386405-2466029"}, {"duration": 5.016, "path": "range/2466030-2545267"}, {"duration": 4.969, "path": "range/2545268-2624769"}, {"duration": 5.015, "path": "range/2624770-2704518"}, {"duration": 5.016, "path": "range/2704519-2783793"}, {"duration": 4.969, "path": "range/2783794-2863043"}, {"duration": 5.016, "path": "range/2863044-2942793"}, {"duration": 5.015, "path": "range/2942794-3022288"}, {"duration": 4.969, "path": "range/3022289-3101428"}, {"duration": 5.016, "path": "range/3101429-3181114"}, {"duration": 5.015, "path": "range/3181115-3260543"}, {"duration": 4.969, "path": "range/3260544-3339859"}, {"duration": 5.016, "path": "range/3339860-3419547"}, {"duration": 5.015, "path": "range/3419548-3498925"}, {"duration": 4.969, "path": "range/3498926-3578370"}, {"duration": 5.016, "path": "range/3578371-3657899"}, {"duration": 5.015, "path": "range/3657900-3737503"}, {"duration": 4.969, "path": "range/3737504-3816594"}, {"duration": 5.016, "path": "range/3816595-3896273"}, {"duration": 5.015, "path": "range/3896274-3975567"}, {"duration": 4.97, "path": "range/3975568-4054974"}, {"duration": 5.015, "path": "range/4054975-4134714"}, {"duration": 5.016, "path": "range/4134715-4213821"}, {"duration": 4.969, "path": "range/4213822-4293583"}, {"duration": 5.015, "path": "range/4293584-4373073"}, {"duration": 5.016, "path": "range/4373074-4452314"}, {"duration": 4.969, "path": "range/4452315-4531837"}, {"duration": 5.015, "path": "range/4531838-4611354"}, {"duration": 5.016, "path": "range/4611355-4690757"}, {"duration": 4.969, "path": "range/4690758-4769908"}, {"duration": 5.015, "path": "range/4769909-4849808"}, {"duration": 5.016, "path": "range/4849809-4929035"}, {"duration": 4.969, "path": "range/4929036-5008287"}, {"duration": 5.015, "path": "range/5008288-5087987"}, {"duration": 5.016, "path": "range/5087988-5167389"}, {"duration": 4.969, "path": "range/5167390-5246829"}, {"duration": 5.015, "path": "range/5246830-5326503"}, {"duration": 5.016, "path": "range/5326504-5405791"}, {"duration": 4.969, "path": "range/5405792-5485380"}, {"duration": 5.016, "path": "range/5485381-5565003"}, {"duration": 5.015, "path": "range/5565004-5644244"}, {"duration": 4.969, "path": "range/5644245-5723654"}, {"duration": 5.016, "path": "range/5723655-5803306"}, {"duration": 5.015, "path": "range/5803307-5882648"}, {"duration": 4.969, "path": "range/5882649-5961908"}, {"duration": 5.016, "path": "range/5961909-6041626"}, {"duration": 5.015, "path": "range/6041627-6121153"}, {"duration": 4.969, "path": "range/6121154-6200313"}, {"duration": 5.016, "path": "range/6200314-6280093"}, {"duration": 5.015, "path": "range/6280094-6359407"}, {"duration": 4.969, "path": "range/6359408-6438683"}, {"duration": 5.016, "path": "range/6438684-6518266"}, {"duration": 5.015, "path": "range/6518267-6597900"}, {"duration": 4.97, "path": "range/6597901-6677113"}, {"duration": 5.015, "path": "range/6677114-6756858"}, {"duration": 5.016, "path": "range/6756859-6836042"}, {"duration": 4.969, "path": "range/6836043-6915394"}, {"duration": 5.015, "path": "range/6915395-6995069"}, {"duration": 5.016, "path": "range/6995070-7074406"}, {"duration": 4.969, "path": "range/7074407-7153762"}, {"duration": 5.015, "path": "range/7153763-7233425"}, {"duration": 5.016, "path": "range/7233426-7312801"}, {"duration": 4.969, "path": "range/7312802-7392131"}, {"duration": 5.015, "path": "range/7392132-7471826"}, {"duration": 5.016, "path": "range/7471827-7551101"}, {"duration": 4.969, "path": "range/7551102-7630612"}, {"duration": 5.015, "path": "range/7630613-7710265"}, {"duration": 5.016, "path": "range/7710266-7789453"}, {"duration": 4.969, "path": "range/7789454-7869044"}, {"duration": 5.015, "path": "range/7869045-7948686"}, {"duration": 5.016, "path": "range/7948687-8028092"}, {"duration": 4.969, "path": "range/8028093-8107303"}, {"duration": 5.016, "path": "range/8107304-8187100"}, {"duration": 5.015, "path": "range/8187101-8266371"}, {"duration": 4.969, "path": "range/8266372-8345731"}, {"duration": 5.016, "path": "range/8345732-8425420"}, {"duration": 5.015, "path": "range/8425421-8504826"}, {"duration": 4.969, "path": "range/8504827-8584152"}, {"duration": 5.016, "path": "range/8584153-8663716"}, {"duration": 5.015, "path": "range/8663717-8743257"}, {"duration": 4.969, "path": "range/8743258-8822434"}, {"duration": 5.016, "path": "range/8822435-8902061"}, {"duration": 5.015, "path": "range/8902062-8981453"}, {"duration": 4.969, "path": "range/8981454-9060859"}, {"duration": 5.016, "path": "range/9060860-9140561"}, {"duration": 5.015, "path": "range/9140562-9219869"}, {"duration": 4.97, "path": "range/9219870-9299351"}, {"duration": 5.015, "path": "range/9299352-9378835"}, {"duration": 5.016, "path": "range/9378836-9458182"}, {"duration": 4.969, "path": "range/9458183-9537860"}, {"duration": 5.015, "path": "range/9537861-9617315"}, {"duration": 5.016, "path": "range/9617316-9696620"}, {"duration": 4.969, "path": "range/9696621-9775792"}, {"duration": 5.015, "path": "range/9775793-9855794"}, {"duration": 5.016, "path": "range/9855795-9935057"}, {"duration": 4.969, "path": "range/9935058-10014402"}, {"duration": 5.015, "path": "range/10014403-10094014"}, {"duration": 5.016, "path": "range/10094015-10173306"}, {"duration": 4.969, "path": "range/10173307-10252616"}, {"duration": 5.015, "path": "range/10252617-10332268"}, {"duration": 5.016, "path": "range/10332269-10411583"}, {"duration": 4.969, "path": "range/10411584-10491203"}, {"duration": 5.015, "path": "range/10491204-10570762"}, {"duration": 5.016, "path": "range/10570763-10650227"}, {"duration": 4.969, "path": "range/10650228-10729346"}, {"duration": 5.016, "path": "range/10729347-10809196"}, {"duration": 5.015, "path": "range/10809197-10888525"}, {"duration": 4.969, "path": "range/10888526-10967739"}, {"duration": 5.016, "path": "range/10967740-11047457"}, {"duration": 5.015, "path": "range/11047458-11126825"}, {"duration": 4.969, "path": "range/11126826-11206045"}, {"duration": 5.016, "path": "range/11206046-11285910"}, {"duration": 5.015, "path": "range/11285911-11365280"}, {"duration": 4.969, "path": "range/11365281-11444462"}, {"duration": 5.016, "path": "range/11444463-11524206"}, {"duration": 5.015, "path": "range/11524207-11603488"}, {"duration": 4.969, "path": "range/11603489-11682989"}, {"duration": 3.808, "path": "range/11682990-11741863"}], "acodec": "mp4a.40.2"}, {"asr": null, "tbr": 108.0, "protocol": "http_dash_segments", "format": "160 - 256x144 (DASH video)", "format_note": "DASH video", "height": 144, "manifest_url": "https://manifest.googlevideo.com/api/manifest/dash/requiressl/yes/source/youtube/id/c9634038a7f0daa9/itag/0/ei/vNnRXIr0I8bgkgaK0rvAAg/playback_host/r6---sn-a5mlrn7k.googlevideo.com/mm/31%2C29/mn/sn-a5mlrn7k%2Csn-a5meknee/ms/au%2Crdu/mv/u/pl/21/hfr/all/as/fmp4_audio_clear%2Cwebm_audio_clear%2Cwebm2_audio_clear%2Cfmp4_sd_hd_clear%2Cwebm2_sd_hd_clear/mt/1557255740/fvip/4/ip/155.94.169.201/ipbits/0/expire/1557278236/sparams/ip%2Cipbits%2Cexpire%2Crequiressl%2Csource%2Cid%2Citag%2Cei%2Cplayback_host%2Cmm%2Cmn%2Cms%2Cmv%2Cpl%2Chfr%2Cas/signature/849D19C69FFBBD64D4FAC80C68938559B44A27A8.7BC9768FD70DBD4F8FEE2C278E2C73E570AFF867/key/yt8", "format_id": "160", "container": "mp4_dash", "language": null, "http_headers": {"Accept-Charset": "ISO-8859-1,utf-8;q=0.7,*;q=0.7", "Accept-Language": "en-us,en;q=0.5", "Accept-Encoding": "gzip, deflate", "Accept": "text/html,application/xhtml+xml,application/xml;q=0.9,*/*;q=0.8", "User-Agent": "Mozilla/5.0 (X11; Linux x86_64; rv:59.0) Gecko/20100101 Firefox/59.0"}, "url": "https://manifest.googlevideo.com/api/manifest/dash/requiressl/yes/source/youtube/id/c9634038a7f0daa9/itag/0/ei/vNnRXIr0I8bgkgaK0rvAAg/playback_host/r6---sn-a5mlrn7k.googlevideo.com/mm/31%2C29/mn/sn-a5mlrn7k%2Csn-a5meknee/ms/au%2Crdu/mv/u/pl/21/hfr/all/as/fmp4_audio_clear%2Cwebm_audio_clear%2Cwebm2_audio_clear%2Cfmp4_sd_hd_clear%2Cwebm2_sd_hd_clear/mt/1557255740/fvip/4/ip/155.94.169.201/ipbits/0/expire/1557278236/sparams/ip%2Cipbits%2Cexpire%2Crequiressl%2Csource%2Cid%2Citag%2Cei%2Cplayback_host%2Cmm%2Cmn%2Cms%2Cmv%2Cpl%2Chfr%2Cas/signature/849D19C69FFBBD64D4FAC80C68938559B44A27A8.7BC9768FD70DBD4F8FEE2C278E2C73E570AFF867/key/yt8", "vcodec": "avc1.4d400b", "width": 256, "ext": "mp4", "fragment_base_url": "https://r6---sn-a5mlrn7k.googlevideo.com/videoplayback/id/c9634038a7f0daa9/itag/160/source/yt_otf/requiressl/yes/ei/vNnRXIr0I8bgkgaK0rvAAg/mm/31,29/mn/sn-a5mlrn7k,sn-a5meknee/ms/au,rdu/mv/u/pl/21/ratebypass/yes/mime/video%2Fmp4/otfp/1/otf/1/lmt/1492905476160860/mt/1557255740/fvip/4/disable_polymer/true/ip/155.94.169.201/ipbits/0/expire/1557278236/sparams/ip,ipbits,expire,id,itag,source,requiressl,ei,mm,mn,ms,mv,pl,ratebypass,mime,otfp,otf,lmt/signature/68899BC609979AE1FA282E97EB1BD12C08C4DE22.9696D91E1351D07359DA364BC27773B537E7F6CB/key/dg_yt0/", "filesize": null, "fps": 30, "fragments": [{"path": "sq/0"}, {"duration": 5.333, "path": "sq/1/dur/5.333"}, {"duration": 5.334, "path": "sq/2/dur/5.334"}, {"duration": 5.333, "path": "sq/3/dur/5.333"}, {"duration": 5.333, "path": "sq/4/dur/5.333"}, {"duration": 5.334, "path": "sq/5/dur/5.334"}, {"duration": 5.333, "path": "sq/6/dur/5.333"}, {"duration": 5.333, "path": "sq/7/dur/5.333"}, {"duration": 5.334, "path": "sq/8/dur/5.334"}, {"duration": 5.333, "path": "sq/9/dur/5.333"}, {"duration": 5.333, "path": "sq/10/dur/5.333"}, {"duration": 5.334, "path": "sq/11/dur/5.334"}, {"duration": 5.333, "path": "sq/12/dur/5.333"}, {"duration": 5.333, "path": "sq/13/dur/5.333"}, {"duration": 5.334, "path": "sq/14/dur/5.334"}, {"duration": 5.333, "path": "sq/15/dur/5.333"}, {"duration": 5.333, "path": "sq/16/dur/5.333"}, {"duration": 5.334, "path": "sq/17/dur/5.334"}, {"duration": 5.333, "path": "sq/18/dur/5.333"}, {"duration": 5.333, "path": "sq/19/dur/5.333"}, {"duration": 5.334, "path": "sq/20/dur/5.334"}, {"duration": 5.333, "path": "sq/21/dur/5.333"}, {"duration": 5.333, "path": "sq/22/dur/5.333"}, {"duration": 5.334, "path": "sq/23/dur/5.334"}, {"duration": 5.333, "path": "sq/24/dur/5.333"}, {"duration": 5.333, "path": "sq/25/dur/5.333"}, {"duration": 5.334, "path": "sq/26/dur/5.334"}, {"duration": 5.333, "path": "sq/27/dur/5.333"}, {"duration": 5.333, "path": "sq/28/dur/5.333"}, {"duration": 5.334, "path": "sq/29/dur/5.334"}, {"duration": 5.333, "path": "sq/30/dur/5.333"}, {"duration": 5.333, "path": "sq/31/dur/5.333"}, {"duration": 5.334, "path": "sq/32/dur/5.334"}, {"duration": 5.333, "path": "sq/33/dur/5.333"}, {"duration": 5.333, "path": "sq/34/dur/5.333"}, {"duration": 5.334, "path": "sq/35/dur/5.334"}, {"duration": 5.333, "path": "sq/36/dur/5.333"}, {"duration": 5.333, "path": "sq/37/dur/5.333"}, {"duration": 5.334, "path": "sq/38/dur/5.334"}, {"duration": 5.333, "path": "sq/39/dur/5.333"}, {"duration": 5.333, "path": "sq/40/dur/5.333"}, {"duration": 5.334, "path": "sq/41/dur/5.334"}, {"duration": 5.333, "path": "sq/42/dur/5.333"}, {"duration": 5.333, "path": "sq/43/dur/5.333"}, {"duration": 5.334, "path": "sq/44/dur/5.334"}, {"duration": 5.333, "path": "sq/45/dur/5.333"}, {"duration": 5.333, "path": "sq/46/dur/5.333"}, {"duration": 5.334, "path": "sq/47/dur/5.334"}, {"duration": 5.333, "path": "sq/48/dur/5.333"}, {"duration": 5.333, "path": "sq/49/dur/5.333"}, {"duration": 5.334, "path": "sq/50/dur/5.334"}, {"duration": 5.333, "path": "sq/51/dur/5.333"}, {"duration": 5.333, "path": "sq/52/dur/5.333"}, {"duration": 5.334, "path": "sq/53/dur/5.334"}, {"duration": 5.333, "path": "sq/54/dur/5.333"}, {"duration": 5.333, "path": "sq/55/dur/5.333"}, {"duration": 5.334, "path": "sq/56/dur/5.334"}, {"duration": 5.333, "path": "sq/57/dur/5.333"}, {"duration": 5.333, "path": "sq/58/dur/5.333"}, {"duration": 5.334, "path": "sq/59/dur/5.334"}, {"duration": 5.333, "path": "sq/60/dur/5.333"}, {"duration": 5.333, "path": "sq/61/dur/5.333"}, {"duration": 5.334, "path": "sq/62/dur/5.334"}, {"duration": 5.333, "path": "sq/63/dur/5.333"}, {"duration": 5.333, "path": "sq/64/dur/5.333"}, {"duration": 5.334, "path": "sq/65/dur/5.334"}, {"duration": 5.333, "path": "sq/66/dur/5.333"}, {"duration": 5.333, "path": "sq/67/dur/5.333"}, {"duration": 5.334, "path": "sq/68/dur/5.334"}, {"duration": 5.333, "path": "sq/69/dur/5.333"}, {"duration": 5.333, "path": "sq/70/dur/5.333"}, {"duration": 5.334, "path": "sq/71/dur/5.334"}, {"duration": 5.333, "path": "sq/72/dur/5.333"}, {"duration": 5.333, "path": "sq/73/dur/5.333"}, {"duration": 5.334, "path": "sq/74/dur/5.334"}, {"duration": 5.333, "path": "sq/75/dur/5.333"}, {"duration": 5.333, "path": "sq/76/dur/5.333"}, {"duration": 5.334, "path": "sq/77/dur/5.334"}, {"duration": 5.333, "path": "sq/78/dur/5.333"}, {"duration": 5.333, "path": "sq/79/dur/5.333"}, {"duration": 5.334, "path": "sq/80/dur/5.334"}, {"duration": 5.333, "path": "sq/81/dur/5.333"}, {"duration": 5.333, "path": "sq/82/dur/5.333"}, {"duration": 5.334, "path": "sq/83/dur/5.334"}, {"duration": 5.333, "path": "sq/84/dur/5.333"}, {"duration": 5.333, "path": "sq/85/dur/5.333"}, {"duration": 5.334, "path": "sq/86/dur/5.334"}, {"duration": 5.333, "path": "sq/87/dur/5.333"}, {"duration": 5.333, "path": "sq/88/dur/5.333"}, {"duration": 5.334, "path": "sq/89/dur/5.334"}, {"duration": 5.333, "path": "sq/90/dur/5.333"}, {"duration": 5.333, "path": "sq/91/dur/5.333"}, {"duration": 5.334, "path": "sq/92/dur/5.334"}, {"duration": 5.333, "path": "sq/93/dur/5.333"}, {"duration": 5.333, "path": "sq/94/dur/5.333"}, {"duration": 5.334, "path": "sq/95/dur/5.334"}, {"duration": 5.333, "path": "sq/96/dur/5.333"}, {"duration": 5.333, "path": "sq/97/dur/5.333"}, {"duration": 5.334, "path": "sq/98/dur/5.334"}, {"duration": 5.333, "path": "sq/99/dur/5.333"}, {"duration": 5.333, "path": "sq/100/dur/5.333"}, {"duration": 5.334, "path": "sq/101/dur/5.334"}, {"duration": 5.333, "path": "sq/102/dur/5.333"}, {"duration": 5.333, "path": "sq/103/dur/5.333"}, {"duration": 5.334, "path": "sq/104/dur/5.334"}, {"duration": 5.333, "path": "sq/105/dur/5.333"}, {"duration": 5.333, "path": "sq/106/dur/5.333"}, {"duration": 5.334, "path": "sq/107/dur/5.334"}, {"duration": 5.333, "path": "sq/108/dur/5.333"}, {"duration": 5.333, "path": "sq/109/dur/5.333"}, {"duration": 5.334, "path": "sq/110/dur/5.334"}, {"duration": 5.333, "path": "sq/111/dur/5.333"}, {"duration": 5.333, "path": "sq/112/dur/5.333"}, {"duration": 5.334, "path": "sq/113/dur/5.334"}, {"duration": 5.333, "path": "sq/114/dur/5.333"}, {"duration": 5.333, "path": "sq/115/dur/5.333"}, {"duration": 5.334, "path": "sq/116/dur/5.334"}, {"duration": 5.333, "path": "sq/117/dur/5.333"}, {"duration": 5.333, "path": "sq/118/dur/5.333"}, {"duration": 5.334, "path": "sq/119/dur/5.334"}, {"duration": 5.333, "path": "sq/120/dur/5.333"}, {"duration": 5.333, "path": "sq/121/dur/5.333"}, {"duration": 5.334, "path": "sq/122/dur/5.334"}, {"duration": 5.333, "path": "sq/123/dur/5.333"}, {"duration": 5.333, "path": "sq/124/dur/5.333"}, {"duration": 5.334, "path": "sq/125/dur/5.334"}, {"duration": 5.333, "path": "sq/126/dur/5.333"}, {"duration": 5.333, "path": "sq/127/dur/5.333"}, {"duration": 5.334, "path": "sq/128/dur/5.334"}, {"duration": 5.333, "path": "sq/129/dur/5.333"}, {"duration": 5.333, "path": "sq/130/dur/5.333"}, {"duration": 5.334, "path": "sq/131/dur/5.334"}, {"duration": 5.333, "path": "sq/132/dur/5.333"}, {"duration": 5.333, "path": "sq/133/dur/5.333"}, {"duration": 5.334, "path": "sq/134/dur/5.334"}, {"duration": 5.333, "path": "sq/135/dur/5.333"}, {"duration": 5.333, "path": "sq/136/dur/5.333"}, {"duration": 5.334, "path": "sq/137/dur/5.334"}, {"duration": 5.333, "path": "sq/138/dur/5.333"}, {"duration": 2.667, "path": "sq/139/dur/2.667"}], "acodec": "none"}, {"asr": null, "tbr": 242.0, "protocol": "http_dash_segments", "format": "133 - 426x240 (DASH video)", "format_note": "DASH video", "height": 240, "manifest_url": "https://manifest.googlevideo.com/api/manifest/dash/requiressl/yes/source/youtube/id/c9634038a7f0daa9/itag/0/ei/vNnRXIr0I8bgkgaK0rvAAg/playback_host/r6---sn-a5mlrn7k.googlevideo.com/mm/31%2C29/mn/sn-a5mlrn7k%2Csn-a5meknee/ms/au%2Crdu/mv/u/pl/21/hfr/all/as/fmp4_audio_clear%2Cwebm_audio_clear%2Cwebm2_audio_clear%2Cfmp4_sd_hd_clear%2Cwebm2_sd_hd_clear/mt/1557255740/fvip/4/ip/155.94.169.201/ipbits/0/expire/1557278236/sparams/ip%2Cipbits%2Cexpire%2Crequiressl%2Csource%2Cid%2Citag%2Cei%2Cplayback_host%2Cmm%2Cmn%2Cms%2Cmv%2Cpl%2Chfr%2Cas/signature/849D19C69FFBBD64D4FAC80C68938559B44A27A8.7BC9768FD70DBD4F8FEE2C278E2C73E570AFF867/key/yt8", "format_id": "133", "container": "mp4_dash", "language": null, "http_headers": {"Accept-Charset": "ISO-8859-1,utf-8;q=0.7,*;q=0.7", "Accept-Language": "en-us,en;q=0.5", "Accept-Encoding": "gzip, deflate", "Accept": "text/html,application/xhtml+xml,application/xml;q=0.9,*/*;q=0.8", "User-Agent": "Mozilla/5.0 (X11; Linux x86_64; rv:59.0) Gecko/20100101 Firefox/59.0"}, "url": "https://manifest.googlevideo.com/api/manifest/dash/requiressl/yes/source/youtube/id/c9634038a7f0daa9/itag/0/ei/vNnRXIr0I8bgkgaK0rvAAg/playback_host/r6---sn-a5mlrn7k.googlevideo.com/mm/31%2C29/mn/sn-a5mlrn7k%2Csn-a5meknee/ms/au%2Crdu/mv/u/pl/21/hfr/all/as/fmp4_audio_clear%2Cwebm_audio_clear%2Cwebm2_audio_clear%2Cfmp4_sd_hd_clear%2Cwebm2_sd_hd_clear/mt/1557255740/fvip/4/ip/155.94.169.201/ipbits/0/expire/1557278236/sparams/ip%2Cipbits%2Cexpire%2Crequiressl%2Csource%2Cid%2Citag%2Cei%2Cplayback_host%2Cmm%2Cmn%2Cms%2Cmv%2Cpl%2Chfr%2Cas/signature/849D19C69FFBBD64D4FAC80C68938559B44A27A8.7BC9768FD70DBD4F8FEE2C278E2C73E570AFF867/key/yt8", "vcodec": "avc1.4d400c", "width": 426, "ext": "mp4", "fragment_base_url": "https://r6---sn-a5mlrn7k.googlevideo.com/videoplayback/id/c9634038a7f0daa9/itag/133/source/yt_otf/requiressl/yes/ei/vNnRXIr0I8bgkgaK0rvAAg/mm/31,29/mn/sn-a5mlrn7k,sn-a5meknee/ms/au,rdu/mv/u/pl/21/ratebypass/yes/mime/video%2Fmp4/otfp/1/otf/1/lmt/1492905476160860/mt/1557255740/fvip/4/disable_polymer/true/ip/155.94.169.201/ipbits/0/expire/1557278236/sparams/ip,ipbits,expire,id,itag,source,requiressl,ei,mm,mn,ms,mv,pl,ratebypass,mime,otfp,otf,lmt/signature/67F926C36D6A03A5FE3E3DA03BBB68BA618DB294.334D4C29E7ABFDA2FF5FECE3F250A4979DB8C5B5/key/dg_yt0/", "filesize": null, "fps": 30, "fragments": [{"path": "sq/0"}, {"duration": 5.333, "path": "sq/1/dur/5.333"}, {"duration": 5.334, "path": "sq/2/dur/5.334"}, {"duration": 5.333, "path": "sq/3/dur/5.333"}, {"duration": 5.333, "path": "sq/4/dur/5.333"}, {"duration": 5.334, "path": "sq/5/dur/5.334"}, {"duration": 5.333, "path": "sq/6/dur/5.333"}, {"duration": 5.333, "path": "sq/7/dur/5.333"}, {"duration": 5.334, "path": "sq/8/dur/5.334"}, {"duration": 5.333, "path": "sq/9/dur/5.333"}, {"duration": 5.333, "path": "sq/10/dur/5.333"}, {"duration": 5.334, "path": "sq/11/dur/5.334"}, {"duration": 5.333, "path": "sq/12/dur/5.333"}, {"duration": 5.333, "path": "sq/13/dur/5.333"}, {"duration": 5.334, "path": "sq/14/dur/5.334"}, {"duration": 5.333, "path": "sq/15/dur/5.333"}, {"duration": 5.333, "path": "sq/16/dur/5.333"}, {"duration": 5.334, "path": "sq/17/dur/5.334"}, {"duration": 5.333, "path": "sq/18/dur/5.333"}, {"duration": 5.333, "path": "sq/19/dur/5.333"}, {"duration": 5.334, "path": "sq/20/dur/5.334"}, {"duration": 5.333, "path": "sq/21/dur/5.333"}, {"duration": 5.333, "path": "sq/22/dur/5.333"}, {"duration": 5.334, "path": "sq/23/dur/5.334"}, {"duration": 5.333, "path": "sq/24/dur/5.333"}, {"duration": 5.333, "path": "sq/25/dur/5.333"}, {"duration": 5.334, "path": "sq/26/dur/5.334"}, {"duration": 5.333, "path": "sq/27/dur/5.333"}, {"duration": 5.333, "path": "sq/28/dur/5.333"}, {"duration": 5.334, "path": "sq/29/dur/5.334"}, {"duration": 5.333, "path": "sq/30/dur/5.333"}, {"duration": 5.333, "path": "sq/31/dur/5.333"}, {"duration": 5.334, "path": "sq/32/dur/5.334"}, {"duration": 5.333, "path": "sq/33/dur/5.333"}, {"duration": 5.333, "path": "sq/34/dur/5.333"}, {"duration": 5.334, "path": "sq/35/dur/5.334"}, {"duration": 5.333, "path": "sq/36/dur/5.333"}, {"duration": 5.333, "path": "sq/37/dur/5.333"}, {"duration": 5.334, "path": "sq/38/dur/5.334"}, {"duration": 5.333, "path": "sq/39/dur/5.333"}, {"duration": 5.333, "path": "sq/40/dur/5.333"}, {"duration": 5.334, "path": "sq/41/dur/5.334"}, {"duration": 5.333, "path": "sq/42/dur/5.333"}, {"duration": 5.333, "path": "sq/43/dur/5.333"}, {"duration": 5.334, "path": "sq/44/dur/5.334"}, {"duration": 5.333, "path": "sq/45/dur/5.333"}, {"duration": 5.333, "path": "sq/46/dur/5.333"}, {"duration": 5.334, "path": "sq/47/dur/5.334"}, {"duration": 5.333, "path": "sq/48/dur/5.333"}, {"duration": 5.333, "path": "sq/49/dur/5.333"}, {"duration": 5.334, "path": "sq/50/dur/5.334"}, {"duration": 5.333, "path": "sq/51/dur/5.333"}, {"duration": 5.333, "path": "sq/52/dur/5.333"}, {"duration": 5.334, "path": "sq/53/dur/5.334"}, {"duration": 5.333, "path": "sq/54/dur/5.333"}, {"duration": 5.333, "path": "sq/55/dur/5.333"}, {"duration": 5.334, "path": "sq/56/dur/5.334"}, {"duration": 5.333, "path": "sq/57/dur/5.333"}, {"duration": 5.333, "path": "sq/58/dur/5.333"}, {"duration": 5.334, "path": "sq/59/dur/5.334"}, {"duration": 5.333, "path": "sq/60/dur/5.333"}, {"duration": 5.333, "path": "sq/61/dur/5.333"}, {"duration": 5.334, "path": "sq/62/dur/5.334"}, {"duration": 5.333, "path": "sq/63/dur/5.333"}, {"duration": 5.333, "path": "sq/64/dur/5.333"}, {"duration": 5.334, "path": "sq/65/dur/5.334"}, {"duration": 5.333, "path": "sq/66/dur/5.333"}, {"duration": 5.333, "path": "sq/67/dur/5.333"}, {"duration": 5.334, "path": "sq/68/dur/5.334"}, {"duration": 5.333, "path": "sq/69/dur/5.333"}, {"duration": 5.333, "path": "sq/70/dur/5.333"}, {"duration": 5.334, "path": "sq/71/dur/5.334"}, {"duration": 5.333, "path": "sq/72/dur/5.333"}, {"duration": 5.333, "path": "sq/73/dur/5.333"}, {"duration": 5.334, "path": "sq/74/dur/5.334"}, {"duration": 5.333, "path": "sq/75/dur/5.333"}, {"duration": 5.333, "path": "sq/76/dur/5.333"}, {"duration": 5.334, "path": "sq/77/dur/5.334"}, {"duration": 5.333, "path": "sq/78/dur/5.333"}, {"duration": 5.333, "path": "sq/79/dur/5.333"}, {"duration": 5.334, "path": "sq/80/dur/5.334"}, {"duration": 5.333, "path": "sq/81/dur/5.333"}, {"duration": 5.333, "path": "sq/82/dur/5.333"}, {"duration": 5.334, "path": "sq/83/dur/5.334"}, {"duration": 5.333, "path": "sq/84/dur/5.333"}, {"duration": 5.333, "path": "sq/85/dur/5.333"}, {"duration": 5.334, "path": "sq/86/dur/5.334"}, {"duration": 5.333, "path": "sq/87/dur/5.333"}, {"duration": 5.333, "path": "sq/88/dur/5.333"}, {"duration": 5.334, "path": "sq/89/dur/5.334"}, {"duration": 5.333, "path": "sq/90/dur/5.333"}, {"duration": 5.333, "path": "sq/91/dur/5.333"}, {"duration": 5.334, "path": "sq/92/dur/5.334"}, {"duration": 5.333, "path": "sq/93/dur/5.333"}, {"duration": 5.333, "path": "sq/94/dur/5.333"}, {"duration": 5.334, "path": "sq/95/dur/5.334"}, {"duration": 5.333, "path": "sq/96/dur/5.333"}, {"duration": 5.333, "path": "sq/97/dur/5.333"}, {"duration": 5.334, "path": "sq/98/dur/5.334"}, {"duration": 5.333, "path": "sq/99/dur/5.333"}, {"duration": 5.333, "path": "sq/100/dur/5.333"}, {"duration": 5.334, "path": "sq/101/dur/5.334"}, {"duration": 5.333, "path": "sq/102/dur/5.333"}, {"duration": 5.333, "path": "sq/103/dur/5.333"}, {"duration": 5.334, "path": "sq/104/dur/5.334"}, {"duration": 5.333, "path": "sq/105/dur/5.333"}, {"duration": 5.333, "path": "sq/106/dur/5.333"}, {"duration": 5.334, "path": "sq/107/dur/5.334"}, {"duration": 5.333, "path": "sq/108/dur/5.333"}, {"duration": 5.333, "path": "sq/109/dur/5.333"}, {"duration": 5.334, "path": "sq/110/dur/5.334"}, {"duration": 5.333, "path": "sq/111/dur/5.333"}, {"duration": 5.333, "path": "sq/112/dur/5.333"}, {"duration": 5.334, "path": "sq/113/dur/5.334"}, {"duration": 5.333, "path": "sq/114/dur/5.333"}, {"duration": 5.333, "path": "sq/115/dur/5.333"}, {"duration": 5.334, "path": "sq/116/dur/5.334"}, {"duration": 5.333, "path": "sq/117/dur/5.333"}, {"duration": 5.333, "path": "sq/118/dur/5.333"}, {"duration": 5.334, "path": "sq/119/dur/5.334"}, {"duration": 5.333, "path": "sq/120/dur/5.333"}, {"duration": 5.333, "path": "sq/121/dur/5.333"}, {"duration": 5.334, "path": "sq/122/dur/5.334"}, {"duration": 5.333, "path": "sq/123/dur/5.333"}, {"duration": 5.333, "path": "sq/124/dur/5.333"}, {"duration": 5.334, "path": "sq/125/dur/5.334"}, {"duration": 5.333, "path": "sq/126/dur/5.333"}, {"duration": 5.333, "path": "sq/127/dur/5.333"}, {"duration": 5.334, "path": "sq/128/dur/5.334"}, {"duration": 5.333, "path": "sq/129/dur/5.333"}, {"duration": 5.333, "path": "sq/130/dur/5.333"}, {"duration": 5.334, "path": "sq/131/dur/5.334"}, {"duration": 5.333, "path": "sq/132/dur/5.333"}, {"duration": 5.333, "path": "sq/133/dur/5.333"}, {"duration": 5.334, "path": "sq/134/dur/5.334"}, {"duration": 5.333, "path": "sq/135/dur/5.333"}, {"duration": 5.333, "path": "sq/136/dur/5.333"}, {"duration": 5.334, "path": "sq/137/dur/5.334"}, {"duration": 5.333, "path": "sq/138/dur/5.333"}, {"duration": 2.667, "path": "sq/139/dur/2.667"}], "acodec": "none"}, {"asr": null, "tbr": 300.792, "protocol": "http_dash_segments", "format": "134 - 640x360 (DASH video)", "format_note": "DASH video", "height": 360, "manifest_url": "https://manifest.googlevideo.com/api/manifest/dash/requiressl/yes/source/youtube/id/c9634038a7f0daa9/itag/0/ei/vNnRXIr0I8bgkgaK0rvAAg/playback_host/r6---sn-a5mlrn7k.googlevideo.com/mm/31%2C29/mn/sn-a5mlrn7k%2Csn-a5meknee/ms/au%2Crdu/mv/u/pl/21/hfr/all/as/fmp4_audio_clear%2Cwebm_audio_clear%2Cwebm2_audio_clear%2Cfmp4_sd_hd_clear%2Cwebm2_sd_hd_clear/mt/1557255740/fvip/4/ip/155.94.169.201/ipbits/0/expire/1557278236/sparams/ip%2Cipbits%2Cexpire%2Crequiressl%2Csource%2Cid%2Citag%2Cei%2Cplayback_host%2Cmm%2Cmn%2Cms%2Cmv%2Cpl%2Chfr%2Cas/signature/849D19C69FFBBD64D4FAC80C68938559B44A27A8.7BC9768FD70DBD4F8FEE2C278E2C73E570AFF867/key/yt8", "format_id": "134", "container": "mp4_dash", "language": null, "http_headers": {"Accept-Charset": "ISO-8859-1,utf-8;q=0.7,*;q=0.7", "Accept-Language": "en-us,en;q=0.5", "Accept-Encoding": "gzip, deflate", "Accept": "text/html,application/xhtml+xml,application/xml;q=0.9,*/*;q=0.8", "User-Agent": "Mozilla/5.0 (X11; Linux x86_64; rv:59.0) Gecko/20100101 Firefox/59.0"}, "url": "https://manifest.googlevideo.com/api/manifest/dash/requiressl/yes/source/youtube/id/c9634038a7f0daa9/itag/0/ei/vNnRXIr0I8bgkgaK0rvAAg/playback_host/r6---sn-a5mlrn7k.googlevideo.com/mm/31%2C29/mn/sn-a5mlrn7k%2Csn-a5meknee/ms/au%2Crdu/mv/u/pl/21/hfr/all/as/fmp4_audio_clear%2Cwebm_audio_clear%2Cwebm2_audio_clear%2Cfmp4_sd_hd_clear%2Cwebm2_sd_hd_clear/mt/1557255740/fvip/4/ip/155.94.169.201/ipbits/0/expire/1557278236/sparams/ip%2Cipbits%2Cexpire%2Crequiressl%2Csource%2Cid%2Citag%2Cei%2Cplayback_host%2Cmm%2Cmn%2Cms%2Cmv%2Cpl%2Chfr%2Cas/signature/849D19C69FFBBD64D4FAC80C68938559B44A27A8.7BC9768FD70DBD4F8FEE2C278E2C73E570AFF867/key/yt8", "vcodec": "avc1.4d401e", "width": 640, "ext": "mp4", "fragment_base_url": "https://r6---sn-a5mlrn7k.googlevideo.com/videoplayback/id/c9634038a7f0daa9/itag/134/source/youtube/requiressl/yes/ei/vNnRXIr0I8bgkgaK0rvAAg/mm/31,29/mn/sn-a5mlrn7k,sn-a5meknee/ms/au,rdu/mv/u/pl/21/ratebypass/yes/mime/video%2Fmp4/otfp/1/gir/yes/clen/16742729/lmt/1492905476161098/dur/738.666/mt/1557255740/fvip/4/disable_polymer/true/ip/155.94.169.201/ipbits/0/expire/1557278236/sparams/ip,ipbits,expire,id,itag,source,requiressl,ei,mm,mn,ms,mv,pl,ratebypass,mime,otfp,gir,clen,lmt,dur/signature/55338B408BE8255A185D74AFA8A9FF3C0D95DAE0.4FBDF317F1F69F2CE567B4BB15FA47BD35D587E1/key/dg_yt0/", "filesize": null, "fps": 30, "fragments": [{"path": "range/0-714"}, {"duration": 5.333, "path": "range/2415-132057"}, {"duration": 5.334, "path": "range/132058-255738"}, {"duration": 5.333, "path": "range/255739-375667"}, {"duration": 5.333, "path": "range/375668-470869"}, {"duration": 5.334, "path": "range/470870-579380"}, {"duration": 5.333, "path": "range/579381-669667"}, {"duration": 5.333, "path": "range/669668-820838"}, {"duration": 5.334, "path": "range/820839-930505"}, {"duration": 5.333, "path": "range/930506-1062799"}, {"duration": 5.333, "path": "range/1062800-1193522"}, {"duration": 5.334, "path": "range/1193523-1323624"}, {"duration": 5.333, "path": "range/1323625-1429031"}, {"duration": 5.333, "path": "range/1429032-1563516"}, {"duration": 5.334, "path": "range/1563517-1655849"}, {"duration": 5.333, "path": "range/1655850-1743853"}, {"duration": 5.333, "path": "range/1743854-1857098"}, {"duration": 5.334, "path": "range/1857099-2031251"}, {"duration": 5.333, "path": "range/2031252-2170010"}, {"duration": 5.333, "path": "range/2170011-2275341"}, {"duration": 5.334, "path": "range/2275342-2377643"}, {"duration": 5.333, "path": "range/2377644-2489339"}, {"duration": 5.333, "path": "range/2489340-2597197"}, {"duration": 5.334, "path": "range/2597198-2743337"}, {"duration": 5.333, "path": "range/2743338-2837494"}, {"duration": 5.333, "path": "range/2837495-2980880"}, {"duration": 5.334, "path": "range/2980881-3148515"}, {"duration": 5.333, "path": "range/3148516-3256713"}, {"duration": 5.333, "path": "range/3256714-3355149"}, {"duration": 5.334, "path": "range/3355150-3555665"}, {"duration": 5.333, "path": "range/3555666-3683817"}, {"duration": 5.333, "path": "range/3683818-3821944"}, {"duration": 5.334, "path": "range/3821945-3930685"}, {"duration": 5.333, "path": "range/3930686-4031748"}, {"duration": 5.333, "path": "range/4031749-4122952"}, {"duration": 5.334, "path": "range/4122953-4220067"}, {"duration": 5.333, "path": "range/4220068-4351862"}, {"duration": 5.333, "path": "range/4351863-4455853"}, {"duration": 5.334, "path": "range/4455854-4558976"}, {"duration": 5.333, "path": "range/4558977-4676817"}, {"duration": 5.333, "path": "range/4676818-4791359"}, {"duration": 5.334, "path": "range/4791360-4898050"}, {"duration": 5.333, "path": "range/4898051-5009379"}, {"duration": 5.333, "path": "range/5009380-5118132"}, {"duration": 5.334, "path": "range/5118133-5219940"}, {"duration": 5.333, "path": "range/5219941-5345179"}, {"duration": 5.333, "path": "range/5345180-5485193"}, {"duration": 5.334, "path": "range/5485194-5603048"}, {"duration": 5.333, "path": "range/5603049-5791272"}, {"duration": 5.333, "path": "range/5791273-5890613"}, {"duration": 5.334, "path": "range/5890614-6007548"}, {"duration": 5.333, "path": "range/6007549-6142884"}, {"duration": 5.333, "path": "range/6142885-6294368"}, {"duration": 5.334, "path": "range/6294369-6411760"}, {"duration": 5.333, "path": "range/6411761-6528444"}, {"duration": 5.333, "path": "range/6528445-6673955"}, {"duration": 5.334, "path": "range/6673956-6758403"}, {"duration": 5.333, "path": "range/6758404-6867724"}, {"duration": 5.333, "path": "range/6867725-6965731"}, {"duration": 5.334, "path": "range/6965732-7091790"}, {"duration": 5.333, "path": "range/7091791-7209288"}, {"duration": 5.333, "path": "range/7209289-7334043"}, {"duration": 5.334, "path": "range/7334044-7454832"}, {"duration": 5.333, "path": "range/7454833-7554595"}, {"duration": 5.333, "path": "range/7554596-7702652"}, {"duration": 5.334, "path": "range/7702653-7822730"}, {"duration": 5.333, "path": "range/7822731-7951952"}, {"duration": 5.333, "path": "range/7951953-8065573"}, {"duration": 5.334, "path": "range/8065574-8185104"}, {"duration": 5.333, "path": "range/8185105-8338905"}, {"duration": 5.333, "path": "range/8338906-8450557"}, {"duration": 5.334, "path": "range/8450558-8611862"}, {"duration": 5.333, "path": "range/8611863-8719555"}, {"duration": 5.333, "path": "range/8719556-8883129"}, {"duration": 5.334, "path": "range/8883130-9023422"}, {"duration": 5.333, "path": "range/9023423-9149796"}, {"duration": 5.333, "path": "range/9149797-9301855"}, {"duration": 5.334, "path": "range/9301856-9425972"}, {"duration": 5.333, "path": "range/9425973-9539207"}, {"duration": 5.333, "path": "range/9539208-9706526"}, {"duration": 5.334, "path": "range/9706527-9827840"}, {"duration": 5.333, "path": "range/9827841-9931954"}, {"duration": 5.333, "path": "range/9931955-10034568"}, {"duration": 5.334, "path": "range/10034569-10200929"}, {"duration": 5.333, "path": "range/10200930-10341066"}, {"duration": 5.333, "path": "range/10341067-10476731"}, {"duration": 5.334, "path": "range/10476732-10592935"}, {"duration": 5.333, "path": "range/10592936-10691524"}, {"duration": 5.333, "path": "range/10691525-10797930"}, {"duration": 5.334, "path": "range/10797931-10909991"}, {"duration": 5.333, "path": "range/10909992-11016866"}, {"duration": 5.333, "path": "range/11016867-11176113"}, {"duration": 5.334, "path": "range/11176114-11295852"}, {"duration": 5.333, "path": "range/11295853-11409203"}, {"duration": 5.333, "path": "range/11409204-11537461"}, {"duration": 5.334, "path": "range/11537462-11629352"}, {"duration": 5.333, "path": "range/11629353-11721714"}, {"duration": 5.333, "path": "range/11721715-11867100"}, {"duration": 5.334, "path": "range/11867101-11971601"}, {"duration": 5.333, "path": "range/11971602-12083318"}, {"duration": 5.333, "path": "range/12083319-12189309"}, {"duration": 5.334, "path": "range/12189310-12319365"}, {"duration": 5.333, "path": "range/12319366-12438302"}, {"duration": 5.333, "path": "range/12438303-12537092"}, {"duration": 5.334, "path": "range/12537093-12660776"}, {"duration": 5.333, "path": "range/12660777-12830326"}, {"duration": 5.333, "path": "range/12830327-12957565"}, {"duration": 5.334, "path": "range/12957566-13075052"}, {"duration": 5.333, "path": "range/13075053-13190489"}, {"duration": 5.333, "path": "range/13190490-13310227"}, {"duration": 5.334, "path": "range/13310228-13494986"}, {"duration": 5.333, "path": "range/13494987-13595187"}, {"duration": 5.333, "path": "range/13595188-13746159"}, {"duration": 5.334, "path": "range/13746160-13891735"}, {"duration": 5.333, "path": "range/13891736-13993478"}, {"duration": 5.333, "path": "range/13993479-14088131"}, {"duration": 5.334, "path": "range/14088132-14178878"}, {"duration": 5.333, "path": "range/14178879-14263006"}, {"duration": 5.333, "path": "range/14263007-14380465"}, {"duration": 5.334, "path": "range/14380466-14512666"}, {"duration": 5.333, "path": "range/14512667-14620244"}, {"duration": 5.333, "path": "range/14620245-14740737"}, {"duration": 5.334, "path": "range/14740738-14860531"}, {"duration": 5.333, "path": "range/14860532-14974763"}, {"duration": 5.333, "path": "range/14974764-15092133"}, {"duration": 5.334, "path": "range/15092134-15207750"}, {"duration": 5.333, "path": "range/15207751-15329633"}, {"duration": 5.333, "path": "range/15329634-15436236"}, {"duration": 5.334, "path": "range/15436237-15532761"}, {"duration": 5.333, "path": "range/15532762-15655511"}, {"duration": 5.333, "path": "range/15655512-15752280"}, {"duration": 5.334, "path": "range/15752281-15869452"}, {"duration": 5.333, "path": "range/15869453-16015517"}, {"duration": 5.333, "path": "range/16015518-16131025"}, {"duration": 5.334, "path": "range/16131026-16245777"}, {"duration": 5.333, "path": "range/16245778-16355925"}, {"duration": 5.333, "path": "range/16355926-16479100"}, {"duration": 5.334, "path": "range/16479101-16579313"}, {"duration": 5.333, "path": "range/16579314-16696990"}, {"duration": 2.667, "path": "range/16696991-16742728"}], "acodec": "none"}, {"asr": null, "tbr": 1155.0, "protocol": "http_dash_segments", "format": "135 - 854x480 (DASH video)", "format_note": "DASH video", "height": 480, "manifest_url": "https://manifest.googlevideo.com/api/manifest/dash/requiressl/yes/source/youtube/id/c9634038a7f0daa9/itag/0/ei/vNnRXIr0I8bgkgaK0rvAAg/playback_host/r6---sn-a5mlrn7k.googlevideo.com/mm/31%2C29/mn/sn-a5mlrn7k%2Csn-a5meknee/ms/au%2Crdu/mv/u/pl/21/hfr/all/as/fmp4_audio_clear%2Cwebm_audio_clear%2Cwebm2_audio_clear%2Cfmp4_sd_hd_clear%2Cwebm2_sd_hd_clear/mt/1557255740/fvip/4/ip/155.94.169.201/ipbits/0/expire/1557278236/sparams/ip%2Cipbits%2Cexpire%2Crequiressl%2Csource%2Cid%2Citag%2Cei%2Cplayback_host%2Cmm%2Cmn%2Cms%2Cmv%2Cpl%2Chfr%2Cas/signature/849D19C69FFBBD64D4FAC80C68938559B44A27A8.7BC9768FD70DBD4F8FEE2C278E2C73E570AFF867/key/yt8", "format_id": "135", "container": "mp4_dash", "language": null, "http_headers": {"Accept-Charset": "ISO-8859-1,utf-8;q=0.7,*;q=0.7", "Accept-Language": "en-us,en;q=0.5", "Accept-Encoding": "gzip, deflate", "Accept": "text/html,application/xhtml+xml,application/xml;q=0.9,*/*;q=0.8", "User-Agent": "Mozilla/5.0 (X11; Linux x86_64; rv:59.0) Gecko/20100101 Firefox/59.0"}, "url": "https://manifest.googlevideo.com/api/manifest/dash/requiressl/yes/source/youtube/id/c9634038a7f0daa9/itag/0/ei/vNnRXIr0I8bgkgaK0rvAAg/playback_host/r6---sn-a5mlrn7k.googlevideo.com/mm/31%2C29/mn/sn-a5mlrn7k%2Csn-a5meknee/ms/au%2Crdu/mv/u/pl/21/hfr/all/as/fmp4_audio_clear%2Cwebm_audio_clear%2Cwebm2_audio_clear%2Cfmp4_sd_hd_clear%2Cwebm2_sd_hd_clear/mt/1557255740/fvip/4/ip/155.94.169.201/ipbits/0/expire/1557278236/sparams/ip%2Cipbits%2Cexpire%2Crequiressl%2Csource%2Cid%2Citag%2Cei%2Cplayback_host%2Cmm%2Cmn%2Cms%2Cmv%2Cpl%2Chfr%2Cas/signature/849D19C69FFBBD64D4FAC80C68938559B44A27A8.7BC9768FD70DBD4F8FEE2C278E2C73E570AFF867/key/yt8", "vcodec": "avc1.4d4014", "width": 854, "ext": "mp4", "fragment_base_url": "https://r6---sn-a5mlrn7k.googlevideo.com/videoplayback/id/c9634038a7f0daa9/itag/135/source/yt_otf/requiressl/yes/ei/vNnRXIr0I8bgkgaK0rvAAg/mm/31,29/mn/sn-a5mlrn7k,sn-a5meknee/ms/au,rdu/mv/u/pl/21/ratebypass/yes/mime/video%2Fmp4/otfp/1/otf/1/lmt/1492905476160860/mt/1557255740/fvip/4/disable_polymer/true/ip/155.94.169.201/ipbits/0/expire/1557278236/sparams/ip,ipbits,expire,id,itag,source,requiressl,ei,mm,mn,ms,mv,pl,ratebypass,mime,otfp,otf,lmt/signature/6E27AE3E045216231C4E092A5AE4CAE91B8CD8E2.1DDBBA69881112E82579D26D259EC8E8A7CC2819/key/dg_yt0/", "filesize": null, "fps": 30, "fragments": [{"path": "sq/0"}, {"duration": 5.333, "path": "sq/1/dur/5.333"}, {"duration": 5.334, "path": "sq/2/dur/5.334"}, {"duration": 5.333, "path": "sq/3/dur/5.333"}, {"duration": 5.333, "path": "sq/4/dur/5.333"}, {"duration": 5.334, "path": "sq/5/dur/5.334"}, {"duration": 5.333, "path": "sq/6/dur/5.333"}, {"duration": 5.333, "path": "sq/7/dur/5.333"}, {"duration": 5.334, "path": "sq/8/dur/5.334"}, {"duration": 5.333, "path": "sq/9/dur/5.333"}, {"duration": 5.333, "path": "sq/10/dur/5.333"}, {"duration": 5.334, "path": "sq/11/dur/5.334"}, {"duration": 5.333, "path": "sq/12/dur/5.333"}, {"duration": 5.333, "path": "sq/13/dur/5.333"}, {"duration": 5.334, "path": "sq/14/dur/5.334"}, {"duration": 5.333, "path": "sq/15/dur/5.333"}, {"duration": 5.333, "path": "sq/16/dur/5.333"}, {"duration": 5.334, "path": "sq/17/dur/5.334"}, {"duration": 5.333, "path": "sq/18/dur/5.333"}, {"duration": 5.333, "path": "sq/19/dur/5.333"}, {"duration": 5.334, "path": "sq/20/dur/5.334"}, {"duration": 5.333, "path": "sq/21/dur/5.333"}, {"duration": 5.333, "path": "sq/22/dur/5.333"}, {"duration": 5.334, "path": "sq/23/dur/5.334"}, {"duration": 5.333, "path": "sq/24/dur/5.333"}, {"duration": 5.333, "path": "sq/25/dur/5.333"}, {"duration": 5.334, "path": "sq/26/dur/5.334"}, {"duration": 5.333, "path": "sq/27/dur/5.333"}, {"duration": 5.333, "path": "sq/28/dur/5.333"}, {"duration": 5.334, "path": "sq/29/dur/5.334"}, {"duration": 5.333, "path": "sq/30/dur/5.333"}, {"duration": 5.333, "path": "sq/31/dur/5.333"}, {"duration": 5.334, "path": "sq/32/dur/5.334"}, {"duration": 5.333, "path": "sq/33/dur/5.333"}, {"duration": 5.333, "path": "sq/34/dur/5.333"}, {"duration": 5.334, "path": "sq/35/dur/5.334"}, {"duration": 5.333, "path": "sq/36/dur/5.333"}, {"duration": 5.333, "path": "sq/37/dur/5.333"}, {"duration": 5.334, "path": "sq/38/dur/5.334"}, {"duration": 5.333, "path": "sq/39/dur/5.333"}, {"duration": 5.333, "path": "sq/40/dur/5.333"}, {"duration": 5.334, "path": "sq/41/dur/5.334"}, {"duration": 5.333, "path": "sq/42/dur/5.333"}, {"duration": 5.333, "path": "sq/43/dur/5.333"}, {"duration": 5.334, "path": "sq/44/dur/5.334"}, {"duration": 5.333, "path": "sq/45/dur/5.333"}, {"duration": 5.333, "path": "sq/46/dur/5.333"}, {"duration": 5.334, "path": "sq/47/dur/5.334"}, {"duration": 5.333, "path": "sq/48/dur/5.333"}, {"duration": 5.333, "path": "sq/49/dur/5.333"}, {"duration": 5.334, "path": "sq/50/dur/5.334"}, {"duration": 5.333, "path": "sq/51/dur/5.333"}, {"duration": 5.333, "path": "sq/52/dur/5.333"}, {"duration": 5.334, "path": "sq/53/dur/5.334"}, {"duration": 5.333, "path": "sq/54/dur/5.333"}, {"duration": 5.333, "path": "sq/55/dur/5.333"}, {"duration": 5.334, "path": "sq/56/dur/5.334"}, {"duration": 5.333, "path": "sq/57/dur/5.333"}, {"duration": 5.333, "path": "sq/58/dur/5.333"}, {"duration": 5.334, "path": "sq/59/dur/5.334"}, {"duration": 5.333, "path": "sq/60/dur/5.333"}, {"duration": 5.333, "path": "sq/61/dur/5.333"}, {"duration": 5.334, "path": "sq/62/dur/5.334"}, {"duration": 5.333, "path": "sq/63/dur/5.333"}, {"duration": 5.333, "path": "sq/64/dur/5.333"}, {"duration": 5.334, "path": "sq/65/dur/5.334"}, {"duration": 5.333, "path": "sq/66/dur/5.333"}, {"duration": 5.333, "path": "sq/67/dur/5.333"}, {"duration": 5.334, "path": "sq/68/dur/5.334"}, {"duration": 5.333, "path": "sq/69/dur/5.333"}, {"duration": 5.333, "path": "sq/70/dur/5.333"}, {"duration": 5.334, "path": "sq/71/dur/5.334"}, {"duration": 5.333, "path": "sq/72/dur/5.333"}, {"duration": 5.333, "path": "sq/73/dur/5.333"}, {"duration": 5.334, "path": "sq/74/dur/5.334"}, {"duration": 5.333, "path": "sq/75/dur/5.333"}, {"duration": 5.333, "path": "sq/76/dur/5.333"}, {"duration": 5.334, "path": "sq/77/dur/5.334"}, {"duration": 5.333, "path": "sq/78/dur/5.333"}, {"duration": 5.333, "path": "sq/79/dur/5.333"}, {"duration": 5.334, "path": "sq/80/dur/5.334"}, {"duration": 5.333, "path": "sq/81/dur/5.333"}, {"duration": 5.333, "path": "sq/82/dur/5.333"}, {"duration": 5.334, "path": "sq/83/dur/5.334"}, {"duration": 5.333, "path": "sq/84/dur/5.333"}, {"duration": 5.333, "path": "sq/85/dur/5.333"}, {"duration": 5.334, "path": "sq/86/dur/5.334"}, {"duration": 5.333, "path": "sq/87/dur/5.333"}, {"duration": 5.333, "path": "sq/88/dur/5.333"}, {"duration": 5.334, "path": "sq/89/dur/5.334"}, {"duration": 5.333, "path": "sq/90/dur/5.333"}, {"duration": 5.333, "path": "sq/91/dur/5.333"}, {"duration": 5.334, "path": "sq/92/dur/5.334"}, {"duration": 5.333, "path": "sq/93/dur/5.333"}, {"duration": 5.333, "path": "sq/94/dur/5.333"}, {"duration": 5.334, "path": "sq/95/dur/5.334"}, {"duration": 5.333, "path": "sq/96/dur/5.333"}, {"duration": 5.333, "path": "sq/97/dur/5.333"}, {"duration": 5.334, "path": "sq/98/dur/5.334"}, {"duration": 5.333, "path": "sq/99/dur/5.333"}, {"duration": 5.333, "path": "sq/100/dur/5.333"}, {"duration": 5.334, "path": "sq/101/dur/5.334"}, {"duration": 5.333, "path": "sq/102/dur/5.333"}, {"duration": 5.333, "path": "sq/103/dur/5.333"}, {"duration": 5.334, "path": "sq/104/dur/5.334"}, {"duration": 5.333, "path": "sq/105/dur/5.333"}, {"duration": 5.333, "path": "sq/106/dur/5.333"}, {"duration": 5.334, "path": "sq/107/dur/5.334"}, {"duration": 5.333, "path": "sq/108/dur/5.333"}, {"duration": 5.333, "path": "sq/109/dur/5.333"}, {"duration": 5.334, "path": "sq/110/dur/5.334"}, {"duration": 5.333, "path": "sq/111/dur/5.333"}, {"duration": 5.333, "path": "sq/112/dur/5.333"}, {"duration": 5.334, "path": "sq/113/dur/5.334"}, {"duration": 5.333, "path": "sq/114/dur/5.333"}, {"duration": 5.333, "path": "sq/115/dur/5.333"}, {"duration": 5.334, "path": "sq/116/dur/5.334"}, {"duration": 5.333, "path": "sq/117/dur/5.333"}, {"duration": 5.333, "path": "sq/118/dur/5.333"}, {"duration": 5.334, "path": "sq/119/dur/5.334"}, {"duration": 5.333, "path": "sq/120/dur/5.333"}, {"duration": 5.333, "path": "sq/121/dur/5.333"}, {"duration": 5.334, "path": "sq/122/dur/5.334"}, {"duration": 5.333, "path": "sq/123/dur/5.333"}, {"duration": 5.333, "path": "sq/124/dur/5.333"}, {"duration": 5.334, "path": "sq/125/dur/5.334"}, {"duration": 5.333, "path": "sq/126/dur/5.333"}, {"duration": 5.333, "path": "sq/127/dur/5.333"}, {"duration": 5.334, "path": "sq/128/dur/5.334"}, {"duration": 5.333, "path": "sq/129/dur/5.333"}, {"duration": 5.333, "path": "sq/130/dur/5.333"}, {"duration": 5.334, "path": "sq/131/dur/5.334"}, {"duration": 5.333, "path": "sq/132/dur/5.333"}, {"duration": 5.333, "path": "sq/133/dur/5.333"}, {"duration": 5.334, "path": "sq/134/dur/5.334"}, {"duration": 5.333, "path": "sq/135/dur/5.333"}, {"duration": 5.333, "path": "sq/136/dur/5.333"}, {"duration": 5.334, "path": "sq/137/dur/5.334"}, {"duration": 5.333, "path": "sq/138/dur/5.333"}, {"duration": 2.667, "path": "sq/139/dur/2.667"}], "acodec": "none"}, {"asr": null, "tbr": 1447.251, "protocol": "http_dash_segments", "format": "136 - 1280x720 (DASH video)", "format_note": "DASH video", "height": 720, "manifest_url": "https://manifest.googlevideo.com/api/manifest/dash/requiressl/yes/source/youtube/id/c9634038a7f0daa9/itag/0/ei/vNnRXIr0I8bgkgaK0rvAAg/playback_host/r6---sn-a5mlrn7k.googlevideo.com/mm/31%2C29/mn/sn-a5mlrn7k%2Csn-a5meknee/ms/au%2Crdu/mv/u/pl/21/hfr/all/as/fmp4_audio_clear%2Cwebm_audio_clear%2Cwebm2_audio_clear%2Cfmp4_sd_hd_clear%2Cwebm2_sd_hd_clear/mt/1557255740/fvip/4/ip/155.94.169.201/ipbits/0/expire/1557278236/sparams/ip%2Cipbits%2Cexpire%2Crequiressl%2Csource%2Cid%2Citag%2Cei%2Cplayback_host%2Cmm%2Cmn%2Cms%2Cmv%2Cpl%2Chfr%2Cas/signature/849D19C69FFBBD64D4FAC80C68938559B44A27A8.7BC9768FD70DBD4F8FEE2C278E2C73E570AFF867/key/yt8", "format_id": "136", "container": "mp4_dash", "language": null, "http_headers": {"Accept-Charset": "ISO-8859-1,utf-8;q=0.7,*;q=0.7", "Accept-Language": "en-us,en;q=0.5", "Accept-Encoding": "gzip, deflate", "Accept": "text/html,application/xhtml+xml,application/xml;q=0.9,*/*;q=0.8", "User-Agent": "Mozilla/5.0 (X11; Linux x86_64; rv:59.0) Gecko/20100101 Firefox/59.0"}, "url": "https://manifest.googlevideo.com/api/manifest/dash/requiressl/yes/source/youtube/id/c9634038a7f0daa9/itag/0/ei/vNnRXIr0I8bgkgaK0rvAAg/playback_host/r6---sn-a5mlrn7k.googlevideo.com/mm/31%2C29/mn/sn-a5mlrn7k%2Csn-a5meknee/ms/au%2Crdu/mv/u/pl/21/hfr/all/as/fmp4_audio_clear%2Cwebm_audio_clear%2Cwebm2_audio_clear%2Cfmp4_sd_hd_clear%2Cwebm2_sd_hd_clear/mt/1557255740/fvip/4/ip/155.94.169.201/ipbits/0/expire/1557278236/sparams/ip%2Cipbits%2Cexpire%2Crequiressl%2Csource%2Cid%2Citag%2Cei%2Cplayback_host%2Cmm%2Cmn%2Cms%2Cmv%2Cpl%2Chfr%2Cas/signature/849D19C69FFBBD64D4FAC80C68938559B44A27A8.7BC9768FD70DBD4F8FEE2C278E2C73E570AFF867/key/yt8", "vcodec": "avc1.4d401f", "width": 1280, "ext": "mp4", "fragment_base_url": "https://r6---sn-a5mlrn7k.googlevideo.com/videoplayback/id/c9634038a7f0daa9/itag/136/source/youtube/requiressl/yes/ei/vNnRXIr0I8bgkgaK0rvAAg/mm/31,29/mn/sn-a5mlrn7k,sn-a5meknee/ms/au,rdu/mv/u/pl/21/ratebypass/yes/mime/video%2Fmp4/otfp/1/gir/yes/clen/91878491/lmt/1492905476160860/dur/738.666/mt/1557255740/fvip/4/disable_polymer/true/ip/155.94.169.201/ipbits/0/expire/1557278236/sparams/ip,ipbits,expire,id,itag,source,requiressl,ei,mm,mn,ms,mv,pl,ratebypass,mime,otfp,gir,clen,lmt,dur/signature/89EB0FFD81D5AB99B37806311798421E67F5E146.9599A01AA01CDDB6C09F2218727B5DDAC3C57488/key/dg_yt0/", "filesize": null, "fps": 30, "fragments": [{"path": "range/0-713"}, {"duration": 5.333, "path": "range/2414-719446"}, {"duration": 5.334, "path": "range/719447-1403348"}, {"duration": 5.333, "path": "range/1403349-2076872"}, {"duration": 5.333, "path": "range/2076873-2637328"}, {"duration": 5.334, "path": "range/2637329-3254256"}, {"duration": 5.333, "path": "range/3254257-3796156"}, {"duration": 5.333, "path": "range/3796157-4565904"}, {"duration": 5.334, "path": "range/4565905-5191900"}, {"duration": 5.333, "path": "range/5191901-5903177"}, {"duration": 5.333, "path": "range/5903178-6623892"}, {"duration": 5.334, "path": "range/6623893-7327146"}, {"duration": 5.333, "path": "range/7327147-7911843"}, {"duration": 5.333, "path": "range/7911844-8643781"}, {"duration": 5.334, "path": "range/8643782-9175919"}, {"duration": 5.333, "path": "range/9175920-9686307"}, {"duration": 5.333, "path": "range/9686308-10316279"}, {"duration": 5.334, "path": "range/10316280-11163381"}, {"duration": 5.333, "path": "range/11163382-11902985"}, {"duration": 5.333, "path": "range/11902986-12498515"}, {"duration": 5.334, "path": "range/12498516-13098430"}, {"duration": 5.333, "path": "range/13098431-13744485"}, {"duration": 5.333, "path": "range/13744486-14368585"}, {"duration": 5.334, "path": "range/14368586-15159709"}, {"duration": 5.333, "path": "range/15159710-15715282"}, {"duration": 5.333, "path": "range/15715283-16469500"}, {"duration": 5.334, "path": "range/16469501-17313060"}, {"duration": 5.333, "path": "range/17313061-17917851"}, {"duration": 5.333, "path": "range/17917852-18495427"}, {"duration": 5.334, "path": "range/18495428-19460201"}, {"duration": 5.333, "path": "range/19460202-20131778"}, {"duration": 5.333, "path": "range/20131779-20873988"}, {"duration": 5.334, "path": "range/20873989-21486927"}, {"duration": 5.333, "path": "range/21486928-22068757"}, {"duration": 5.333, "path": "range/22068758-22596947"}, {"duration": 5.334, "path": "range/22596948-23143466"}, {"duration": 5.333, "path": "range/23143467-23853815"}, {"duration": 5.333, "path": "range/23853816-24442125"}, {"duration": 5.334, "path": "range/24442126-25046288"}, {"duration": 5.333, "path": "range/25046289-25710296"}, {"duration": 5.333, "path": "range/25710297-26353765"}, {"duration": 5.334, "path": "range/26353766-26958496"}, {"duration": 5.333, "path": "range/26958497-27597208"}, {"duration": 5.333, "path": "range/27597209-28218275"}, {"duration": 5.334, "path": "range/28218276-28803477"}, {"duration": 5.333, "path": "range/28803478-29499540"}, {"duration": 5.333, "path": "range/29499541-30250805"}, {"duration": 5.334, "path": "range/30250806-30918238"}, {"duration": 5.333, "path": "range/30918239-31830966"}, {"duration": 5.333, "path": "range/31830967-32395746"}, {"duration": 5.334, "path": "range/32395747-33032567"}, {"duration": 5.333, "path": "range/33032568-33755080"}, {"duration": 5.333, "path": "range/33755081-34568795"}, {"duration": 5.334, "path": "range/34568796-35220690"}, {"duration": 5.333, "path": "range/35220691-35879965"}, {"duration": 5.333, "path": "range/35879966-36665920"}, {"duration": 5.334, "path": "range/36665921-37175010"}, {"duration": 5.333, "path": "range/37175011-37795385"}, {"duration": 5.333, "path": "range/37795386-38374426"}, {"duration": 5.334, "path": "range/38374427-39065759"}, {"duration": 5.333, "path": "range/39065760-39724186"}, {"duration": 5.333, "path": "range/39724187-40412135"}, {"duration": 5.334, "path": "range/40412136-41081472"}, {"duration": 5.333, "path": "range/41081473-41670382"}, {"duration": 5.333, "path": "range/41670383-42445475"}, {"duration": 5.334, "path": "range/42445476-43113997"}, {"duration": 5.333, "path": "range/43113998-43832023"}, {"duration": 5.333, "path": "range/43832024-44471524"}, {"duration": 5.334, "path": "range/44471525-45132790"}, {"duration": 5.333, "path": "range/45132791-45963538"}, {"duration": 5.333, "path": "range/45963539-46581280"}, {"duration": 5.334, "path": "range/46581281-47445515"}, {"duration": 5.333, "path": "range/47445516-48055032"}, {"duration": 5.333, "path": "range/48055033-48916296"}, {"duration": 5.334, "path": "range/48916297-49681825"}, {"duration": 5.333, "path": "range/49681826-50371227"}, {"duration": 5.333, "path": "range/50371228-51174018"}, {"duration": 5.334, "path": "range/51174019-51866564"}, {"duration": 5.333, "path": "range/51866565-52499531"}, {"duration": 5.333, "path": "range/52499532-53381320"}, {"duration": 5.334, "path": "range/53381321-54072943"}, {"duration": 5.333, "path": "range/54072944-54672778"}, {"duration": 5.333, "path": "range/54672779-55264894"}, {"duration": 5.334, "path": "range/55264895-56092688"}, {"duration": 5.333, "path": "range/56092689-56837538"}, {"duration": 5.333, "path": "range/56837539-57575818"}, {"duration": 5.334, "path": "range/57575819-58233993"}, {"duration": 5.333, "path": "range/58233994-58811733"}, {"duration": 5.333, "path": "range/58811734-59430481"}, {"duration": 5.334, "path": "range/59430482-60090091"}, {"duration": 5.333, "path": "range/60090092-60714296"}, {"duration": 5.333, "path": "range/60714297-61523492"}, {"duration": 5.334, "path": "range/61523493-62200677"}, {"duration": 5.333, "path": "range/62200678-62851699"}, {"duration": 5.333, "path": "range/62851700-63551107"}, {"duration": 5.334, "path": "range/63551108-64078456"}, {"duration": 5.333, "path": "range/64078457-64624004"}, {"duration": 5.333, "path": "range/64624005-65408500"}, {"duration": 5.334, "path": "range/65408501-66013369"}, {"duration": 5.333, "path": "range/66013370-66641703"}, {"duration": 5.333, "path": "range/66641704-67236037"}, {"duration": 5.334, "path": "range/67236038-67941440"}, {"duration": 5.333, "path": "range/67941441-68578767"}, {"duration": 5.333, "path": "range/68578768-69129011"}, {"duration": 5.334, "path": "range/69129012-69799979"}, {"duration": 5.333, "path": "range/69799980-70626328"}, {"duration": 5.333, "path": "range/70626329-71311237"}, {"duration": 5.334, "path": "range/71311238-71949871"}, {"duration": 5.333, "path": "range/71949872-72558881"}, {"duration": 5.333, "path": "range/72558882-73216459"}, {"duration": 5.334, "path": "range/73216460-74119435"}, {"duration": 5.333, "path": "range/74119436-74677949"}, {"duration": 5.333, "path": "range/74677950-75437841"}, {"duration": 5.334, "path": "range/75437842-76199173"}, {"duration": 5.333, "path": "range/76199174-76762000"}, {"duration": 5.333, "path": "range/76762001-77301613"}, {"duration": 5.334, "path": "range/77301614-77819040"}, {"duration": 5.333, "path": "range/77819041-78299654"}, {"duration": 5.333, "path": "range/78299655-78940928"}, {"duration": 5.334, "path": "range/78940929-79641488"}, {"duration": 5.333, "path": "range/79641489-80239088"}, {"duration": 5.333, "path": "range/80239089-80890762"}, {"duration": 5.334, "path": "range/80890763-81544787"}, {"duration": 5.333, "path": "range/81544788-82176685"}, {"duration": 5.333, "path": "range/82176686-82819494"}, {"duration": 5.334, "path": "range/82819495-83467214"}, {"duration": 5.333, "path": "range/83467215-84124194"}, {"duration": 5.333, "path": "range/84124195-84719037"}, {"duration": 5.334, "path": "range/84719038-85260282"}, {"duration": 5.333, "path": "range/85260283-85931568"}, {"duration": 5.333, "path": "range/85931569-86485664"}, {"duration": 5.334, "path": "range/86485665-87136579"}, {"duration": 5.333, "path": "range/87136580-87884281"}, {"duration": 5.333, "path": "range/87884282-88491314"}, {"duration": 5.334, "path": "range/88491315-89116455"}, {"duration": 5.333, "path": "range/89116456-89735111"}, {"duration": 5.333, "path": "range/89735112-90399010"}, {"duration": 5.334, "path": "range/90399011-90965060"}, {"duration": 5.333, "path": "range/90965061-91618614"}, {"duration": 2.667, "path": "range/91618615-91878490"}], "acodec": "none"}, {"http_headers": {"Accept-Charset": "ISO-8859-1,utf-8;q=0.7,*;q=0.7", "Accept-Language": "en-us,en;q=0.5", "Accept-Encoding": "gzip, deflate", "Accept": "text/html,application/xhtml+xml,application/xml;q=0.9,*/*;q=0.8", "User-Agent": "Mozilla/5.0 (X11; Linux x86_64; rv:59.0) Gecko/20100101 Firefox/59.0"}, "protocol": "https", "format": "18 - 640x360 (medium)", "url": "https://r6---sn-a5mlrn7k.googlevideo.com/videoplayback?id=o-AGI1ctXdIUn-uHV_SPTZe5cV-lwWJXpOXuH4QD3C92nH&itag=18&source=youtube&requiressl=yes&mm=31%2C29&mn=sn-a5mlrn7k%2Csn-a5meknee&ms=au%2Crdu&mv=u&pl=21&ei=vNnRXIr0I8bgkgaK0rvAAg&mime=video%2Fmp4&gir=yes&clen=34346387&ratebypass=yes&dur=738.719&lmt=1492905479160346&mt=1557255740&fvip=4&c=WEB&ip=155.94.169.201&ipbits=0&expire=1557278236&sparams=ip%2Cipbits%2Cexpire%2Cid%2Citag%2Csource%2Crequiressl%2Cmm%2Cmn%2Cms%2Cmv%2Cpl%2Cei%2Cmime%2Cgir%2Cclen%2Cratebypass%2Cdur%2Clmt&signature=48C2A28AB8098200D8A6141FF552A9F1515CA0D0.80B8881EC22C1948854FB53AC816BFFB1C02DA72&key=yt8", "quality": 1, "vcodec": "avc1.42001E", "format_note": "medium", "ext": "mp4", "player_url": "/yts/jsbin/player_ias-vflisCO7O/en_US/base.js", "width": 640, "abr": 96, "filesize": 34346387, "format_id": "18", "height": 360, "resolution": "640x360", "acodec": "mp4a.40.2"}, {"http_headers": {"Accept-Charset": "ISO-8859-1,utf-8;q=0.7,*;q=0.7", "Accept-Language": "en-us,en;q=0.5", "Accept-Encoding": "gzip, deflate", "Accept": "text/html,application/xhtml+xml,application/xml;q=0.9,*/*;q=0.8", "User-Agent": "Mozilla/5.0 (X11; Linux x86_64; rv:59.0) Gecko/20100101 Firefox/59.0"}, "protocol": "https", "format": "43 - 640x360 (medium)", "url": "https://r6---sn-a5mlrn7k.googlevideo.com/videoplayback?id=o-AGI1ctXdIUn-uHV_SPTZe5cV-lwWJXpOXuH4QD3C92nH&itag=43&source=youtube&requiressl=yes&mm=31%2C29&mn=sn-a5mlrn7k%2Csn-a5meknee&ms=au%2Crdu&mv=u&pl=21&ei=vNnRXIr0I8bgkgaK0rvAAg&mime=video%2Fwebm&gir=yes&clen=51562554&ratebypass=yes&dur=0.000&lmt=1492908141011019&mt=1557255740&fvip=4&c=WEB&ip=155.94.169.201&ipbits=0&expire=1557278236&sparams=ip%2Cipbits%2Cexpire%2Cid%2Citag%2Csource%2Crequiressl%2Cmm%2Cmn%2Cms%2Cmv%2Cpl%2Cei%2Cmime%2Cgir%2Cclen%2Cratebypass%2Cdur%2Clmt&signature=F121521AE685BB72A8B77476E3D8F45C6CC5CBC5.2C58E21ACE24CCC2B06BD676635412D566498A21&key=yt8", "quality": 1, "vcodec": "vp8.0", "format_note": "medium", "ext": "webm", "player_url": "/yts/jsbin/player_ias-vflisCO7O/en_US/base.js", "width": 640, "abr": 128, "filesize": 51562554, "format_id": "43", "height": 360, "resolution": "640x360", "acodec": "vorbis"}, {"http_headers": {"Accept-Charset": "ISO-8859-1,utf-8;q=0.7,*;q=0.7", "Accept-Language": "en-us,en;q=0.5", "Accept-Encoding": "gzip, deflate", "Accept": "text/html,application/xhtml+xml,application/xml;q=0.9,*/*;q=0.8", "User-Agent": "Mozilla/5.0 (X11; Linux x86_64; rv:59.0) Gecko/20100101 Firefox/59.0"}, "protocol": "https", "format": "22 - 1280x720 (hd720)", "url": "https://r6---sn-a5mlrn7k.googlevideo.com/videoplayback?id=o-AGI1ctXdIUn-uHV_SPTZe5cV-lwWJXpOXuH4QD3C92nH&itag=22&source=youtube&requiressl=yes&mm=31%2C29&mn=sn-a5mlrn7k%2Csn-a5meknee&ms=au%2Crdu&mv=u&pl=21&ei=vNnRXIr0I8bgkgaK0rvAAg&mime=video%2Fmp4&ratebypass=yes&dur=738.719&lmt=1492905490564877&mt=1557255740&fvip=4&c=WEB&ip=155.94.169.201&ipbits=0&expire=1557278236&sparams=ip%2Cipbits%2Cexpire%2Cid%2Citag%2Csource%2Crequiressl%2Cmm%2Cmn%2Cms%2Cmv%2Cpl%2Cei%2Cmime%2Cratebypass%2Cdur%2Clmt&signature=73BD6E59C553E0C7CA6D0518E576A2386B3F0438.60E7452A56622933B98E1691E8624E120989E1FD&key=yt8", "quality": 2, "vcodec": "avc1.64001F", "format_note": "hd720", "ext": "mp4", "player_url": "/yts/jsbin/player_ias-vflisCO7O/en_US/base.js", "width": 1280, "abr": 192, "format_id": "22", "height": 720, "resolution": "1280x720", "acodec": "mp4a.40.2"}], "playlist_uploader_id": "UCheuDxi3s2WAefGCbLHwqAw", "channel_url": "http://www.youtube.com/channel/UCheuDxi3s2WAefGCbLHwqAw", "resolution": null, "width": 256, "n_entries": 227, "age_limit": 0}